{
  "resonance_analysis": {
    "three_periods_aligned": "否",
    "alignment_direction": "不共振",
    "description": "周线强势多头突破上轨，日线顶背离死叉，小时线破下轨加速下跌，三周期严重矛盾。",
    "contradiction": "周线多头与日线死叉、小时线空头形成对抗，多空分歧剧烈。",
    "dominant_period_state": "周线仍处强势多头主升结构"
  },
  "scenario_analysis": [
    {
      "probability_rank": 1,
      "scenario": "小时线超跌反弹修复",
      "probability_judgment": "概率较大",
      "trigger_conditions": [
        "条件1：小时线收盘站回4553下轨上方",
        "条件2：小时线MACD绿柱缩短或形成金叉",
        "条件3：反弹不破4673中轨则仍是弱势修复"
      ]
    },
    {
      "probability_rank": 2,
      "scenario": "日线回调拖累周线",
      "probability_judgment": "需要条件配合",
      "trigger_conditions": [
        "条件1：日线收盘跌破4603中轨支撑",
        "条件2：周线价格回落至4677上轨下方",
        "条件3：日线MACD绿柱继续放大且跌破零轴"
      ]
    },
    {
      "probability_rank": 3,
      "scenario": "周线强行续涨",
      "probability_judgment": "风险存在",
      "trigger_conditions": [
        "条件1：日线MACD重新金叉化解背离",
        "条件2：价格带量突破4905日线上轨",
        "条件3：小时线形成双底且站上4793上轨"
      ]
    }
  ],
  "key_levels": {
    "resistance": [4673, 4793, 4905],
    "support": [4553, 4603, 4300]
  },
  "confidence_score": 4,
  "confidence_reason": "三周期信号严重矛盾，周线多头与日线、小时线空头对抗，方向不明，置信度较低。",
  "core_observation": "日线顶背离死叉与小时线超跌共存，关注超跌反弹能否传导至日线级别修复。",
  "summary": "周线趋势虽多，但日线背离死叉警示回调风险，小时线已超跌。未出现明确共振信号前，宜观望，等待小时线企稳或日线重新转强。",
  "risk_warning": "以上仅为技术面分析，不构成任何交易建议。期货风险极高，请理性对待。"
}